proxystore_ex/__init__.py
proxystore_ex/py.typed
proxystore_ex/connectors/__init__.py
proxystore_ex/connectors/daos.py
proxystore_ex/connectors/dim/__init__.py
proxystore_ex/connectors/dim/exceptions.py
proxystore_ex/connectors/dim/margo.py
proxystore_ex/connectors/dim/models.py
proxystore_ex/connectors/dim/ucx.py
proxystore_ex/connectors/dim/utils.py
proxystore_ex/connectors/dim/zmq.py
proxystore_ex/plugins/__init__.py
proxystore_ex/plugins/distributed.py
proxystore_ex-0.1.4.dist-info/LICENSE
proxystore_ex-0.1.4.dist-info/METADATA
proxystore_ex-0.1.4.dist-info/WHEEL
proxystore_ex-0.1.4.dist-info/top_level.txt
proxystore_ex-0.1.4.dist-info/RECORD
